rbom/__init__.py
rbom/__main__.py
rbom/commands.py
rbom/example.rbom.yaml
rbom/parsers/__init__.py
rbom/parsers/rbom_parser.py
rbom/policies/__init__.py
rbom/policies/policy_handler.py
rbom/policies/policy_ids.py
rbom/policies/policy_sources.py
rbom/policies/providers/__init__.py
rbom/policies/providers/rbom_policy_handler_github.py
rbom-0.1.5.dist-info/METADATA
rbom-0.1.5.dist-info/WHEEL
rbom-0.1.5.dist-info/entry_points.txt
rbom-0.1.5.dist-info/licenses/LICENSE
rbom-0.1.5.dist-info/RECORD
