Metadata-Version: 2.4
Name: rbom
Version: 0.1.5
Summary: Release Bill of Materials (RBOM)
Project-URL: Homepage, https://github.com/spockops/rbom
Project-URL: Issues, https://github.com/spockops/rbom/issues
Author-email: Example Author <dev@spockops.com>
License-Expression: Apache-2.0
License-File: LICENSE
Keywords: bom,compliance,rbom,release bill of materials,release management,sbom,security,software bill of materials,spockops
Classifier: Development Status :: 4 - Beta
Classifier: Intended Audience :: Developers
Classifier: Intended Audience :: Education
Classifier: Intended Audience :: End Users/Desktop
Classifier: Intended Audience :: Financial and Insurance Industry
Classifier: Intended Audience :: Healthcare Industry
Classifier: Intended Audience :: Information Technology
Classifier: Intended Audience :: Legal Industry
Classifier: Intended Audience :: Manufacturing
Classifier: Intended Audience :: Other Audience
Classifier: Intended Audience :: Science/Research
Classifier: Intended Audience :: System Administrators
Classifier: Intended Audience :: Telecommunications Industry
Classifier: License :: OSI Approved :: Apache Software License
Classifier: Operating System :: OS Independent
Classifier: Programming Language :: Python :: 3
Classifier: Topic :: Security
Classifier: Topic :: Software Development :: Build Tools
Requires-Python: >=3.11
Requires-Dist: click>=8.2.1
Requires-Dist: cryptography>=45.0.2
Requires-Dist: pygithub>=2.6.1
Requires-Dist: pytest>=8.3.5
Requires-Dist: pyyaml>=6.0.2
Requires-Dist: twine>=6.1.0
Provides-Extra: dev
Requires-Dist: pytest>=7.0.0; extra == 'dev'
